{"stats":{"minecraft:custom":{"minecraft:time_since_rest":415,"minecraft:open_chest":1,"minecraft:deaths":18,"minecraft:damage_absorbed":438,"minecraft:play_one_minute":51458,"minecraft:crouch_one_cm":16206,"minecraft:sprint_one_cm":132229,"minecraft:damage_taken":5263,"minecraft:walk_one_cm":148984,"minecraft:sneak_time":5422,"minecraft:walk_under_water_one_cm":15652,"minecraft:drop":1,"minecraft:jump":577,"minecraft:damage_dealt":550,"minecraft:leave_game":2,"minecraft:time_since_death":386,"minecraft:walk_on_water_one_cm":3731,"minecraft:swim_one_cm":2577,"minecraft:fall_one_cm":9932,"minecraft:fly_one_cm":465419,"minecraft:player_kills":8},"minecraft:dropped":{"minecraft:minecart":1},"minecraft:killed_by":{"minecraft:player":5},"minecraft:used":{"minecraft:golden_apple":14,"minecraft:stone_sword":43,"minecraft:diamond_shovel":872,"minecraft:bow":111,"minecraft:barrier":2,"minecraft:egg":15},"minecraft:picked_up":{"minecraft:barrier":1,"minecraft:redstone_block":3,"minecraft:arrow":2,"minecraft:red_wool":1,"minecraft:minecart":1},"minecraft:mined":{"minecraft:snow_block":861}},"DataVersion":1631}